{"count": 8, "results": [{"_class": "course_review", "id": 29754750, "content": "I am learning too much from this course , is very great course to work with php", "rating": 4.5, "created": "2019-04-06T03:28:19Z", "modified": "2020-05-24T01:29:25Z", "user_modified": "2020-05-24T01:29:25Z", "user": {"_class": "user", "id": 29380112, "title": "Waheeb Qatina", "name": "Waheeb", "display_name": "Waheeb Qatina", "image_50x50": "https://img-c.udemycdn.com/user/50x50/anonymous_3.png", "initials": "WQ"}, "response": null, "content_html": "<p>I am learning too much from this course , is very great course to work with php</p>", "created_formatted_with_time_since": "2 years ago"}, {"_class": "course_review", "id": 27649376, "content": "I thought this was a really good course and I had a lot of fun going through. I had no php or mysql experience before I took this course but I'm a lot more comfortable with both topics now\n\nthank's you :)", "rating": 4.5, "created": "2019-02-20T02:01:23Z", "modified": "2019-02-25T01:53:11Z", "user_modified": "2019-02-25T01:53:11Z", "user": {"_class": "user", "id": 63552962, "title": "Jenah othmane", "name": "Jenah", "display_name": "Jenah othmane", "image_50x50": "https://img-c.udemycdn.com/user/50x50/anonymous_3.png", "initials": "JO"}, "response": null, "content_html": "<p>I thought this was a really good course and I had a lot of fun going through. I had no php or mysql experience before I took this course but I'm a lot more comfortable with both topics now</p>\n\n<p>thank's you :)</p>", "created_formatted_with_time_since": "2 years ago"}, {"_class": "course_review", "id": 10445540, "content": "I thought this was a really good course and I had a lot of fun going through.  I had no php or mysql experience before I took this course but I'm a lot more comfortable with both topics now.  My only problem was the instructor did leave his cursor over the lines he was typing which made it a little hard to see what I should type.", "rating": 4.5, "created": "2017-10-22T16:32:48Z", "modified": "2018-05-22T15:17:26Z", "user_modified": "2017-10-23T06:42:39Z", "user": {"_class": "user", "id": 31910236, "title": "Alfred O'Connor", "name": "Alfred", "display_name": "Alfred O'Connor", "image_50x50": "https://img-c.udemycdn.com/user/50x50/anonymous_3.png", "initials": "AO"}, "response": null, "content_html": "<p>I thought this was a really good course and I had a lot of fun going through.  I had no php or mysql experience before I took this course but I'm a lot more comfortable with both topics now.  My only problem was the instructor did leave his cursor over the lines he was typing which made it a little hard to see what I should type.</p>", "created_formatted_with_time_since": "3 years ago"}, {"_class": "course_review", "id": 10386598, "content": "Obecavajuci pocetak", "rating": 5.0, "created": "2017-10-20T01:14:21Z", "modified": "2018-05-22T15:17:09Z", "user_modified": "2017-10-20T07:12:24Z", "user": {"_class": "user", "id": 30534650, "title": "Dusan Vukelic", "name": "Dusan", "display_name": "Dusan Vukelic", "image_50x50": "https://img-c.udemycdn.com/user/50x50/anonymous_3.png", "initials": "DV"}, "response": null, "content_html": "<p>Obecavajuci pocetak</p>", "created_formatted_with_time_since": "3 years ago"}, {"_class": "course_review", "id": 61890622, "content": "INFORMATION IS EXCELLENT. BUT INSTRUCTION GOING ROCKET FAST. NOT SUIT FOR ALL BEGINNERS. LITTLE BIT DISAPPOINTMENT.", "rating": 2.5, "created": "2020-07-22T00:55:14Z", "modified": "2020-07-23T07:20:26Z", "user_modified": "2020-07-23T07:20:26Z", "user": {"_class": "user", "id": 123284184, "title": "Anantharaman", "name": "Anantharaman", "display_name": "Anantharaman", "image_50x50": "https://img-c.udemycdn.com/user/50x50/anonymous_3.png", "initials": "A"}, "response": null, "content_html": "<p>INFORMATION IS EXCELLENT. BUT INSTRUCTION GOING ROCKET FAST. NOT SUIT FOR ALL BEGINNERS. LITTLE BIT DISAPPOINTMENT.</p>", "created_formatted_with_time_since": "a year ago"}, {"_class": "course_review", "id": 9139518, "content": "very infomative :)", "rating": 4.5, "created": "2017-08-29T01:10:37Z", "modified": "2018-05-22T15:15:32Z", "user_modified": "2017-09-11T01:29:45Z", "user": {"_class": "user", "id": 27469766, "title": "Gideon Erasmus", "name": "Gideon", "display_name": "Gideon Erasmus", "image_50x50": "https://img-c.udemycdn.com/user/50x50/anonymous_3.png", "initials": "GE"}, "response": null, "content_html": "<p>very infomative :)</p>", "created_formatted_with_time_since": "4 years ago"}, {"_class": "course_review", "id": 53158676, "content": "poor explanation and voice", "rating": 4.0, "created": "2020-04-29T22:14:21Z", "modified": "2020-05-01T23:51:10Z", "user_modified": "2020-05-01T23:51:10Z", "user": {"_class": "user", "id": 115431194, "title": "Andrean Earl Erasmo", "name": "Andrean Earl", "display_name": "Andrean Earl Erasmo", "image_50x50": "https://img-c.udemycdn.com/user/50x50/anonymous_3.png", "initials": "AE"}, "response": null, "content_html": "<p>poor explanation and voice</p>", "created_formatted_with_time_since": "a year ago"}, {"_class": "course_review", "id": 9787144, "content": "because it is only for windows users so Its confusing for me to follow", "rating": 0.5, "created": "2017-09-25T06:19:14Z", "modified": "2018-05-22T15:16:31Z", "user_modified": "2017-09-25T06:19:14Z", "user": {"_class": "user", "id": 36621618, "title": "Lina Aljared", "name": "Lina", "display_name": "Lina Aljared", "image_50x50": "https://img-c.udemycdn.com/user/50x50/anonymous_3.png", "initials": "LA"}, "response": {"_class": "course_review_response", "id": 731566, "content": "PHP installation is done on Windows only, and recommendations are given for other systems. this is said in the course description and also in the free videos so i don't understand this low review.", "created": "2017-09-27T09:19:25Z", "modified": "2017-09-27T09:19:25Z", "user": {"_class": "user", "id": 16931358, "title": "Fast & Easy Programming", "name": "Fast & Easy", "display_name": "Fast & Easy Programming", "image_50x50": "https://img-c.udemycdn.com/user/50x50/16931358_3cb1_2.jpg", "initials": "FP"}, "content_html": "<p>PHP installation is done on Windows only, and recommendations are given for other systems. this is said in the course description and also in the free videos so i don't understand this low review.</p>", "created_formatted_with_time_since": "4 years ago"}, "content_html": "<p>because it is only for windows users so Its confusing for me to follow</p>", "created_formatted_with_time_since": "4 years ago"}]}