{"count": 1, "results": [{"_class": "course_review", "id": 72548740, "content": "No explanation on anything.", "rating": 2.0, "created": "2020-12-11T11:32:10-08:00", "modified": "2020-12-12T15:06:19-08:00", "user_modified": "2020-12-11T11:32:51-08:00", "user": {"_class": "user", "id": 300316, "title": "Leandro", "name": "Leandro", "display_name": "Leandro", "image_50x50": "https://img-c.udemycdn.com/user/50x50/anonymous_3.png", "initials": "L", "public_display_name": "Leandro"}, "response": null, "content_html": "<p>No explanation on anything.</p>", "created_formatted_with_time_since": "a year ago"}]}