{"count": 3, "results": [{"_class": "course_review", "id": 56439428, "content": "Pace is very fast. Need time to digest....", "rating": 3.5, "created": "2020-05-26T06:40:47Z", "modified": "2020-05-27T08:09:19Z", "user_modified": "2020-05-26T08:03:04Z", "user": {"_class": "user", "id": 119874804, "title": "Jim Brogoitti", "name": "Jim", "display_name": "Jim Brogoitti", "image_50x50": "https://img-c.udemycdn.com/user/50x50/anonymous_3.png", "initials": "JB"}, "response": {"_class": "course_review_response", "id": 5136378, "content": "The course has prerequisites and fast paced by design", "created": "2020-05-27T09:01:54Z", "modified": "2020-05-27T09:01:54Z", "user": {"_class": "user", "id": 5581552, "title": "Laurence Svekis", "name": "Laurence", "display_name": "Laurence Svekis", "image_50x50": "https://img-c.udemycdn.com/user/50x50/5581552_b409_23.jpg", "initials": "LS"}, "content_html": "<p>The course has prerequisites and fast paced by design</p>", "created_formatted_with_time_since": "a year ago"}, "content_html": "<p>Pace is very fast. Need time to digest....</p>", "created_formatted_with_time_since": "a year ago"}, {"_class": "course_review", "id": 47474524, "content": "Molto rapido nelle spiegazioni forse troppo ma un ottimo corso / esempio per approfondire la materia", "rating": 5.0, "created": "2020-03-17T06:39:46Z", "modified": "2020-03-18T02:50:55Z", "user_modified": "2020-03-18T02:50:55Z", "user": {"_class": "user", "id": 9078750, "title": "Flavio Pezzini", "name": "Flavio", "display_name": "Flavio Pezzini", "image_50x50": "https://img-c.udemycdn.com/user/50x50/anonymous_3.png", "initials": "FP"}, "response": {"_class": "course_review_response", "id": 4289556, "content": "Thank you for your support", "created": "2020-03-18T06:57:30Z", "modified": "2020-03-18T06:57:30Z", "user": {"_class": "user", "id": 5581552, "title": "Laurence Svekis", "name": "Laurence", "display_name": "Laurence Svekis", "image_50x50": "https://img-c.udemycdn.com/user/50x50/5581552_b409_23.jpg", "initials": "LS"}, "content_html": "<p>Thank you for your support</p>", "created_formatted_with_time_since": "a year ago"}, "content_html": "<p>Molto rapido nelle spiegazioni forse troppo ma un ottimo corso / esempio per approfondire la materia</p>", "created_formatted_with_time_since": "a year ago"}, {"_class": "course_review", "id": 41885614, "content": "I really appreciate the speed of the lessons so far. Not too fast and not too slow.", "rating": 5.0, "created": "2019-12-13T07:35:44Z", "modified": "2019-12-13T19:08:09Z", "user_modified": "2019-12-13T09:58:38Z", "user": {"_class": "user", "id": 55689288, "title": "Brandy Foster", "name": "Brandy", "display_name": "Brandy Foster", "image_50x50": "https://img-c.udemycdn.com/user/50x50/anonymous_3.png", "initials": "BF"}, "response": {"_class": "course_review_response", "id": 3673158, "content": "Thank you for the wonderful review and feedback, I so happy to have you as a student for the  course.  Let me know if you have any questions.  Best Wishes", "created": "2019-12-14T12:24:27Z", "modified": "2019-12-14T12:24:27Z", "user": {"_class": "user", "id": 5581552, "title": "Laurence Svekis", "name": "Laurence", "display_name": "Laurence Svekis", "image_50x50": "https://img-c.udemycdn.com/user/50x50/5581552_b409_23.jpg", "initials": "LS"}, "content_html": "<p>Thank you for the wonderful review and feedback, I so happy to have you as a student for the  course.  Let me know if you have any questions.  Best Wishes</p>", "created_formatted_with_time_since": "a year ago"}, "content_html": "<p>I really appreciate the speed of the lessons so far. Not too fast and not too slow.</p>", "created_formatted_with_time_since": "a year ago"}]}